mddrt/__init__.py
mddrt/actions.py
mddrt/drt_parameters.py
mddrt/log_formatter.py
mddrt/tree_builder.py
mddrt/tree_diagrammer.py
mddrt/tree_grouper.py
mddrt/tree_node.py
mddrt/utils/__init__.py
mddrt/utils/actions.py
mddrt/utils/builder.py
mddrt/utils/color_schemes.py
mddrt/utils/constants.py
mddrt/utils/diagrammer.py
mddrt/utils/misc.py
mddrt-0.0.8.dist-info/METADATA
mddrt-0.0.8.dist-info/WHEEL
mddrt-0.0.8.dist-info/licenses/LICENSE
mddrt-0.0.8.dist-info/RECORD
