Metadata-Version: 2.3
Name: mddrt
Version: 0.0.8
Summary: Package for Multi-Dimension Directly Rooted Trees visualization
Project-URL: Homepage, https://github.com/nicoabarca/mddrt
Project-URL: Issues, https://github.com/nicoabarca/mddrt/issues
License: MIT License
License-File: LICENSE
Classifier: Intended Audience :: Developers
Classifier: Intended Audience :: Science/Research
Classifier: Operating System :: OS Independent
Classifier: Programming Language :: Python :: 3
Classifier: Topic :: Scientific/Engineering :: Visualization
Requires-Python: >=3.9
Requires-Dist: graphviz
Requires-Dist: numpy
Requires-Dist: pandas
Requires-Dist: pyarrow
Requires-Dist: tqdm
